cpu/register_file_64_bit.v
`default_nettype none
`timescale 1ns/1ns

module register_file_64_bit (E , clk , read_register1 , read_register2 , write_register , write_data , register_write , read_data1 , read_data2);
    input  E , clk; 
    input [4:0] read_register1;
    input [4:0] read_register2;
    input [4:0] write_register;
    input [63:0] write_data;
    input register_write;
    output reg [63:0] read_data1;
    output reg [63:0] read_data2;
    reg [63:0] Q[0:63];

    integer i;
    initial begin
        for (i = 0; i < 64; i = i+1) begin
            Q[i] = 64'b0;
        end
    end

    always @(posedge clk)
    begin
        if (E)
            if(register_write) 
                Q[write_register] = write_data;

        read_data1 = Q[read_register1];
        read_data2 = Q[read_register2];
    end

endmodule

register_file/register_file_64_bit_tb.v
`default_nettype none
`timescale 1ns/1ns

`include "register_file_64_bit.v"

module register_file_64_bit_tb;
    reg E , clk;
    reg [4:0] read_register1;
    reg [4:0] read_register2;
    reg [4:0] write_register;
    reg [63:0] write_data;
    reg register_write;
    wire [63:0] read_data1;
    wire [63:0] read_data2;

    register_file_64_bit registerFile (.E(E) , .clk(clk), .read_register1(read_register1) , .read_register2(read_register2) , .write_register(write_register) ,
    .write_data(write_data) , .register_write(register_write) , .read_data1(read_data1) , .read_data2(read_data2));
    
    parameter delay = 20;

    initial begin
        $dumpfile("register_file_64_bit_tb.vcd");
        $dumpvars(0,register_file_64_bit_tb);


        E = 0;
        clk = 0;
        read_register1 = 10;
        read_register2 = 22;
        write_register = 22;
        write_data = 48;
        register_write = 1;
        #delay 

        clk = 1;
        #delay 

        E = 1;
        clk=0;
        #delay

        clk = 1;
        #delay

        E = 0;
        clk = 0;
        read_register1 = 10;
        read_register2 = 14;
        write_register = 10;
        write_data = 48;
        register_write = 0;
        #delay 

        clk = 1;
        #delay 

        E = 1;
        clk=0;
        #delay

        clk = 1;
        register_write = 1;
        #delay



        E = 0;
        clk = 0;
        read_register1 = 10;
        read_register2 = 14;
        write_register = 22;
        write_data = 48;
        register_write = 1;
        #delay 

        clk = 1;
        #delay 

        E = 1;
        clk=0;
        #delay

        clk = 1;
        #delay 

        $display("Finish");
    end

endmodule

part1/register_file/register_file_64_bit_tb.vcd
$date
	Sat Dec 25 01:40:47 2021
$end
$version
	Icarus Verilog
$end
$timescale
	1ns
$end
$scope module register_file_64_bit_tb $end
$var wire 64 ! read_data2 [63:0] $end
$var wire 64 " read_data1 [63:0] $end
$var reg 1 # E $end
$var reg 1 $ clk $end
$var reg 5 % read_register1 [4:0] $end
$var reg 5 & read_register2 [4:0] $end
$var reg 1 ' register_write $end
$var reg 64 ( write_data [63:0] $end
$var reg 5 ) write_register [4:0] $end
$scope module registerFile $end
$var wire 1 # E $end
$var wire 1 $ clk $end
$var wire 5 * read_register1 [4:0] $end
$var wire 5 + read_register2 [4:0] $end
$var wire 1 ' register_write $end
$var wire 64 , write_data [63:0] $end
$var wire 5 - write_register [4:0] $end
$var reg 64 . read_data1 [63:0] $end
$var reg 64 / read_data2 [63:0] $end
$var integer 32 0 i [31:0] $end
$upscope $end
$upscope $end
$enddefinitions $end
#0
$dumpvars
b1000000 0
bx /
bx .
b10110 -
b110000 ,
b10110 +
b1010 *
b10110 )
b110000 (
1'
b10110 &
b1010 %
0$
0#
bx "
bx !
$end
#20
b0 !
b0 /
b0 "
b0 .
1$
#40
0$
1#
#60
b110000 !
b110000 /
1$
#80
0'
b1010 )
b1010 -
b1110 &
b1110 +
0$
0#
#100
b0 !
b0 /
1$
#120
0$
1#
#140
b110000 "
b110000 .
1'
1$
#160
b10110 )
b10110 -
0$
0#
#180
1$
#200
0$
1#
