dec4_16.v
module dec2to4 (W, Y, En);
    input [1:0] W;
    input En;
    output reg [0:3] Y;
    always @(W, En)
    begin
        if (En == 0)
            Y = 4'b0000;
        else
            case (W)
            0: Y = 4'b1000;
            1: Y = 4'b0100;
            2: Y = 4'b0010;
            3: Y = 4'b0001;
            endcase
    end
endmodule


module dec4to16 (W, Y, En);
    input [3:0] W;
    input En;
    output [0:15] Y;
    wire [0:3] M;

    dec2to4 Dec1 (W[3:2], M[0:3], En);
    dec2to4 Dec2 (W[1:0], Y[0:3], M[0]);
    dec2to4 Dec3 (W[1:0], Y[4:7], M[1]);
    dec2to4 Dec4 (W[1:0], Y[8:11], M[2]);
    dec2to4 Dec5 (W[1:0], Y[12:15], M[3]);
    
endmodule

dec4_16_tb.v
`default_nettype none
`timescale 1ns/1ns
`include "dec4_16.v"

module dec4_16_tb;
reg [3:0] W;
wire [0:15] Y;
reg En;
integer i=0;
parameter delay = 20;

dec4to16 UUT (.W(W),  .Y(Y), .En(En));


initial begin
    $dumpfile("dec4_16_tb.vcd");
    $dumpvars(0, dec4_16_tb);

    En=1;
    W[0] = 0;
    W[1] = 0;
    W[2] = 0;
    W[3] = 0;
 
    for (i = 0 ; i < 15 ; i++) 
        begin
            if(Y[i] == 1 && i!=0) 
                $display("Test Failed");
            if(Y[0] != 1 ) 
                $display("Test Failed");    
        end

  #delay;


    En=1;
    W[0] = 1;
    W[1] = 0;
    W[2] = 0;
    W[3] = 0;
 
    for (i = 0 ; i < 15 ; i++) 
        begin
            if(Y[i] == 1 && i!=1) 
                $display("Test Failed");
            if(Y[1] != 1 ) 
                $display("Test Failed");    
        end

  #delay;

     En=1;
    W[0] = 0;
    W[1] = 1;
    W[2] = 0;
    W[3] = 0;
 
    for (i = 0 ; i < 15 ; i++) 
        begin
            if(Y[i] == 1 && i!=2) 
                $display("Test Failed");
            if(Y[2] != 1 ) 
                $display("Test Failed");    
        end

  #delay;

    En=1;
    W[0] = 1;
    W[1] = 1;
    W[2] = 0;
    W[3] = 0;
 
    for (i = 0 ; i < 15 ; i++) 
        begin
            if(Y[i] == 1 && i!=3) 
                $display("Test Failed");
            if(Y[3] != 1 ) 
                $display("Test Failed");    
        end

  #delay;

    En=1;
    W[0] = 0;
    W[1] = 0;
    W[2] = 1;
    W[3] = 0;
 
    for (i = 0 ; i < 15 ; i++) 
        begin
            if(Y[i] == 1 && i!=4) 
                $display("Test Failed");
            if(Y[4] != 1 ) 
                $display("Test Failed");    
        end

  #delay;

    En=1;
    W[0] = 1;
    W[1] = 0;
    W[2] = 1;
    W[3] = 0;
 
    for (i = 0 ; i < 15 ; i++) 
        begin
            if(Y[i] == 1 && i!=5) 
                $display("Test Failed");
            if(Y[5] != 1 ) 
                $display("Test Failed");    
        end

  #delay;

    En=1;
    W[0] = 0;
    W[1] = 1;
    W[2] = 1;
    W[3] = 0;
 
    for (i = 0 ; i < 15 ; i++) 
        begin
            if(Y[i] == 1 && i!=6) 
                $display("Test Failed");
            if(Y[6] != 1 ) 
                $display("Test Failed");    
        end

  #delay;

    En=1;
    W[0] = 1;
    W[1] = 1;
    W[2] = 1;
    W[3] = 0;
 
    for (i = 0 ; i < 15 ; i++) 
        begin
            if(Y[i] == 1 && i!=7) 
                $display("Test Failed");
            if(Y[7] != 1 ) 
                $display("Test Failed");    
        end

  #delay;

    En=1;
    W[0] = 0;
    W[1] = 0;
    W[2] = 0;
    W[3] = 1;
 
    for (i = 0 ; i < 15 ; i++) 
        begin
            if(Y[i] == 1 && i!=8) 
                $display("Test Failed");
            if(Y[8] != 1 ) 
                $display("Test Failed");    
        end

  #delay;

    En=1;
    W[0] = 1;
    W[1] = 0;
    W[2] = 0;
    W[3] = 1;
 
    for (i = 0 ; i < 15 ; i++) 
        begin
            if(Y[i] == 1 && i!=9) 
                $display("Test Failed");
            if(Y[9] != 1 ) 
                $display("Test Failed");    
        end

  #delay;

    En=1;
    W[0] = 0;
    W[1] = 1;
    W[2] = 0;
    W[3] = 1;
 
    for (i = 0 ; i < 15 ; i++) 
        begin
            if(Y[i] == 1 && i!=10) 
                $display("Test Failed");
            if(Y[10] != 1 ) 
                $display("Test Failed");    
        end

  #delay;
 
    En=1;
    W[0] = 1;
    W[1] = 1;
    W[2] = 0;
    W[3] = 1;
 
    for (i = 0 ; i < 15 ; i++) 
        begin
            if(Y[i] == 1 && i!=11) 
                $display("Test Failed");
            if(Y[11] != 1 ) 
                $display("Test Failed");    
        end

  #delay;
   
    En=0g;
    W[0] = 0;
    W[1] = 0;
    W[2] = 1;
    W[3] = 1;
 
    for (i = 0 ; i < 15 ; i++) 
        begin
            if(Y[i] == 1 && i!=12) 
                $display("Test Failed");
            if(Y[12] != 1 ) 
                $display("Test Failed");    
        end

  #delay;

    En=0;
    W[0] = 1;
    W[1] = 0;
    W[2] = 1;
    W[3] = 1;
  
    for (i = 0 ; i < 15 ; i++) 
        begin
            if(Y[i] == 1 && i!=13) 
                $display("Test Failed");
            if(Y[13] != 1 ) 
                $display("Test Failed");    
        end

  #delay;

    En=0;
    W[0] = 0;
    W[1] = 1;
    W[2] = 1;
    W[3] = 1;
 
    for (i = 0 ; i < 15 ; i++) 
        begin
            if(Y[i] == 1 && i!=14) 
                $display("Test Failed");
            if(Y[14] != 1 ) 
                $display("Test Failed");    
        end

  #delay;

    En=1;
    W[0] = 1;
    W[1] = 1;
    W[2] = 1;
    W[3] = 1;
 
    for (i = 0 ; i < 15 ; i++) 
        begin
            if(Y[i] == 1 && i!=15) 
                $display("Test Failed");
            if(Y[15] != 1 ) 
                $display("Test Failed");    
        end

  #delay;

    

    $display("Test Complete");
   
end

endmodule

dec4_16_tb.vcd
$date
	Mon Nov 22 01:53:33 2021
$end
$version
	Icarus Verilog
$end
$timescale
	10ps
$end
$scope module dec4_16_tb $end
$var wire 16 ! Y [0:15] $end
$var reg 1 " En $end
$var reg 4 # W [3:0] $end
$var integer 32 $ i [31:0] $end
$scope module UUT $end
$var wire 1 " En $end
$var wire 4 % W [3:0] $end
$var wire 16 & Y [0:15] $end
$var wire 4 ' M [0:3] $end
$scope module Dec1 $end
$var wire 1 " En $end
$var wire 2 ( W [1:0] $end
$var reg 4 ) Y [0:3] $end
$upscope $end
$scope module Dec2 $end
$var wire 1 * En $end
$var wire 2 + W [1:0] $end
$var reg 4 , Y [0:3] $end
$upscope $end
$scope module Dec3 $end
$var wire 1 - En $end
$var wire 2 . W [1:0] $end
$var reg 4 / Y [0:3] $end
$upscope $end
$scope module Dec4 $end
$var wire 1 0 En $end
$var wire 2 1 W [1:0] $end
$var reg 4 2 Y [0:3] $end
$upscope $end
$scope module Dec5 $end
$var wire 1 3 En $end
$var wire 2 4 W [1:0] $end
$var reg 4 5 Y [0:3] $end
$upscope $end
$upscope $end
$upscope $end
$enddefinitions $end
#0
$dumpvars
b0 5
b0 4
03
b0 2
b0 1
00
b0 /
b0 .
0-
b0 ,
b0 +
0*
b0 )
b0 (
b0 '
b0 &
b0 %
b1111 $
b0 #
0"
b0 !
$end
#2000
b1 +
b1 .
b1 1
b1 4
b1111 $
b1 #
b1 %
#4000
b10 +
b10 .
b10 1
b10 4
b1111 $
b10 #
b10 %
#6000
b11 +
b11 .
b11 1
b11 4
b1111 $
b11 #
b11 %
#8000
b1 (
b0 +
b0 .
b0 1
b0 4
b1111 $
b100 #
b100 %
#10000
b1 +
b1 .
b1 1
b1 4
b1111 $
b101 #
b101 %
#12000
b10 +
b10 .
b10 1
b10 4
b1111 $
b110 #
b110 %
#14000
b11 +
b11 .
b11 1
b11 4
b1111 $
b111 #
b111 %
#16000
b10 (
b0 +
b0 .
b0 1
b0 4
b1111 $
b1000 #
b1000 %
#18000
b1 +
b1 .
b1 1
b1 4
b1111 $
b1001 #
b1001 %
#20000
b10 +
b10 .
b10 1
b10 4
b1111 $
b1010 #
b1010 %
#22000
b11 +
b11 .
b11 1
b11 4
b1111 $
b1011 #
b1011 %
#24000
b11 (
b0 +
b0 .
b0 1
b0 4
b1111 $
b1100 #
b1100 %
#26000
b1 +
b1 .
b1 1
b1 4
b1111 $
b1101 #
b1101 %
#28000
b10 +
b10 .
b10 1
b10 4
b1111 $
b1110 #
b1110 %
#30000
b11 +
b11 .
b11 1
b11 4
b1111 $
b1111 #
b1111 %
