part1/data_memory/data_memory_64_bit.v
`default_nettype none
`timescale 1ns/1ns

module data_memory_64_bit(clk , E , address , write_data , mem_write , mem_read , read_data);
    input clk , E;
    input [63:0] address;
    input [63:0] write_data;
    input mem_write , mem_read;
    output reg [63:0] read_data;
    reg [63:0] Q [0:1023];

    always @(posedge clk)
    if (E)
    begin
        if(mem_write) 
            Q[address] = write_data;
        if(mem_read)
            read_data = Q[address];
    end
endmodule

data_memory/data_memory_64_bit_tb.v
`default_nettype none
`timescale 1ns/1ns

`include "data_memory_64_bit.v"

module data_memory_64_bit_tb;
    reg clk , E;
    reg [63:0] address;
    reg [63:0] write_data;
    reg mem_write , mem_read;
    wire [63:0] read_data;
    data_memory_64_bit data_memory(.clk(clk), .E(E), .address(address), .write_data(write_data), .mem_write(mem_write), .mem_read(mem_read), .read_data(read_data));
    parameter delay = 20;

    initial begin
        $dumpfile("data_memory_64_bit_tb.vcd");
        $dumpvars(0,data_memory_64_bit_tb);

        E = 1;
        clk = 1;
        mem_write = 1;
        mem_read = 0;
        address = 23;
        write_data = 48;
        #delay

        clk = 0;
        #delay

        clk = 1;
        mem_write = 0;
        mem_read = 1;

        #delay

        clk = 0;
        #delay

        clk = 1;
        mem_write = 1;
        mem_read = 1;
        #delay

        clk = 0;
        mem_write = 0;
        mem_read = 0;
        #delay

        clk = 1;
        mem_write = 1;
        mem_read = 0;
        write_data = 28;
        #delay

        clk = 0;
        #delay

        E = 0;
        clk = 1;
        mem_write = 0;
        mem_read = 0;
        #delay

        E = 1;
        clk = 0;
        mem_write = 0;
        mem_read = 0;
        #delay

        clk = 1;
        mem_write = 1;
        mem_read = 1;
        #delay

        clk = 0;
        mem_write = 0;
        mem_read = 1;
        #delay

        clk = 1;
        mem_write = 1;
        mem_read = 0;
        #delay

        clk = 0;
        mem_write = 1;
        mem_read = 1;
        #delay
 
        $display("Finish");
    end

endmodule

data_memory/data_memory_64_bit_tb.vcd
$date
	Sat Dec 25 16:30:15 2021
$end
$version
	Icarus Verilog
$end
$timescale
	1ns
$end
$scope module data_memory_64_bit_tb $end
$var wire 64 ! read_data [63:0] $end
$var reg 1 " E $end
$var reg 64 # address [63:0] $end
$var reg 1 $ clk $end
$var reg 1 % mem_read $end
$var reg 1 & mem_write $end
$var reg 64 ' write_data [63:0] $end
$scope module data_memory $end
$var wire 1 " E $end
$var wire 64 ( address [63:0] $end
$var wire 1 $ clk $end
$var wire 1 % mem_read $end
$var wire 1 & mem_write $end
$var wire 64 ) write_data [63:0] $end
$var reg 64 * read_data [63:0] $end
$upscope $end
$upscope $end
$enddefinitions $end
#0
$dumpvars
bx *
b110000 )
b10111 (
b110000 '
1&
0%
1$
b10111 #
1"
bx !
$end
#20
0$
#40
b110000 !
b110000 *
1%
0&
1$
#60
0$
#80
1&
1$
#100
0%
0&
0$
#120
b11100 '
b11100 )
1&
1$
#140
0$
#160
0&
1$
0"
#180
0$
1"
#200
b11100 !
b11100 *
1%
1&
1$
#220
0&
0$
#240
0%
1&
1$
#260
1%
0$
